<?xml version="1.0" encoding="utf-8"?>
<DemoData2 xmlns:xsd="http://www.w3.org/2001/XMLSchema" xmlns:xsi="http://www.w3.org/2001/XMLSchema-instance">
  <Uniforms>
    <Uniform>
      <UniformName>p5XTranslation</UniformName>
      <Keyframes>
        <Keyframe>
          <Time>0</Time>
          <Value>-10</Value>
        </Keyframe>
        <Keyframe>
          <Time>100</Time>
          <Value>-3.5</Value>
        </Keyframe>
      </Keyframes>
    </Uniform>
    <Uniform>
      <UniformName>p5XRotation</UniformName>
      <Keyframes>
        <Keyframe>
          <Time>0</Time>
          <Value>-90</Value>
        </Keyframe>
        <Keyframe>
          <Time>100</Time>
          <Value>-90</Value>
        </Keyframe>
      </Keyframes>
    </Uniform>
    <Uniform>
      <UniformName>p6ZTranslation</UniformName>
      <Keyframes>
        <Keyframe>
          <Time>0</Time>
          <Value>-7</Value>
        </Keyframe>
        <Keyframe>
          <Time>100</Time>
          <Value>0</Value>
        </Keyframe>
      </Keyframes>
    </Uniform>
    <Uniform>
      <UniformName>p6XRotation</UniformName>
      <Keyframes>
        <Keyframe>
          <Time>0</Time>
          <Value>90</Value>
        </Keyframe>
        <Keyframe>
          <Time>100</Time>
          <Value>90</Value>
        </Keyframe>
      </Keyframes>
    </Uniform>
    <Uniform>
      <UniformName>p4XTranslation</UniformName>
      <Keyframes>
        <Keyframe>
          <Time>0</Time>
          <Value>10</Value>
        </Keyframe>
        <Keyframe>
          <Time>100</Time>
          <Value>3.5</Value>
        </Keyframe>
      </Keyframes>
    </Uniform>
    <Uniform>
      <UniformName>p4ZRotation</UniformName>
      <Keyframes>
        <Keyframe>
          <Time>0</Time>
          <Value>90</Value>
        </Keyframe>
        <Keyframe>
          <Time>100</Time>
          <Value>90</Value>
        </Keyframe>
      </Keyframes>
    </Uniform>
    <Uniform>
      <UniformName>p3YTranslation</UniformName>
      <Keyframes>
        <Keyframe>
          <Time>0</Time>
          <Value>12.5</Value>
        </Keyframe>
        <Keyframe>
          <Time>100</Time>
          <Value>5.5</Value>
        </Keyframe>
      </Keyframes>
    </Uniform>
    <Uniform>
      <UniformName>p3XRotation</UniformName>
      <Keyframes>
        <Keyframe>
          <Time>0</Time>
          <Value>0</Value>
        </Keyframe>
        <Keyframe>
          <Time>100</Time>
          <Value>0</Value>
        </Keyframe>
      </Keyframes>
    </Uniform>
    <Uniform>
      <UniformName>p2YTranslation</UniformName>
      <Keyframes>
        <Keyframe>
          <Time>0</Time>
          <Value>-5.5</Value>
        </Keyframe>
        <Keyframe>
          <Time>100</Time>
          <Value>-1.5</Value>
        </Keyframe>
      </Keyframes>
    </Uniform>
    <Uniform>
      <UniformName>p2XRotation</UniformName>
      <Keyframes>
        <Keyframe>
          <Time>0</Time>
          <Value>180</Value>
        </Keyframe>
        <Keyframe>
          <Time>100</Time>
          <Value>180</Value>
        </Keyframe>
      </Keyframes>
    </Uniform>
    <Uniform>
      <UniformName>p1ZTranslation</UniformName>
      <Keyframes>
        <Keyframe>
          <Time>0</Time>
          <Value>14</Value>
        </Keyframe>
        <Keyframe>
          <Time>100</Time>
          <Value>7</Value>
        </Keyframe>
      </Keyframes>
    </Uniform>
    <Uniform>
      <UniformName>p1XRotation</UniformName>
      <Keyframes>
        <Keyframe>
          <Time>0</Time>
          <Value>-90</Value>
        </Keyframe>
        <Keyframe>
          <Time>100</Time>
          <Value>-90</Value>
        </Keyframe>
      </Keyframes>
    </Uniform>
  </Uniforms>
  <Tracks>
    <Track>
      <Name>sum</Name>
      <ShaderKeyframes>
        <ShaderKeyframe>
          <Time>0</Time>
          <ShaderPath>.\header_example.glsl</ShaderPath>
        </ShaderKeyframe>
      </ShaderKeyframes>
    </Track>
  </Tracks>
  <Textures />
  <SoundFileName />
</DemoData2>