<?xml version="1.0" encoding="utf-8"?>
<DemoData2 xmlns:xsd="http://www.w3.org/2001/XMLSchema" xmlns:xsi="http://www.w3.org/2001/XMLSchema-instance">
  <Uniforms>
    <Uniform>
      <UniformName>mainCamX</UniformName>
      <Keyframes>
        <Keyframe>
          <Time>0</Time>
          <Value>0</Value>
        </Keyframe>
        <Keyframe>
          <Time>1.04</Time>
          <Value>0</Value>
        </Keyframe>
        <Keyframe>
          <Time>3.01</Time>
          <Value>-1</Value>
        </Keyframe>
        <Keyframe>
          <Time>5.42</Time>
          <Value>0</Value>
        </Keyframe>
        <Keyframe>
          <Time>7.01</Time>
          <Value>0</Value>
        </Keyframe>
        <Keyframe>
          <Time>8.94</Time>
          <Value>-0.72272265</Value>
        </Keyframe>
        <Keyframe>
          <Time>10.32</Time>
          <Value>0.283876628</Value>
        </Keyframe>
        <Keyframe>
          <Time>12.0073328</Time>
          <Value>0</Value>
        </Keyframe>
        <Keyframe>
          <Time>15.87</Time>
          <Value>-0.189184755</Value>
        </Keyframe>
        <Keyframe>
          <Time>19.9816685</Time>
          <Value>0</Value>
        </Keyframe>
        <Keyframe>
          <Time>21.63</Time>
          <Value>0</Value>
        </Keyframe>
        <Keyframe>
          <Time>25.0229149</Time>
          <Value>0</Value>
        </Keyframe>
        <Keyframe>
          <Time>29.27</Time>
          <Value>-1.07546008</Value>
        </Keyframe>
        <Keyframe>
          <Time>31.9890022</Time>
          <Value>0</Value>
        </Keyframe>
        <Keyframe>
          <Time>116.062859</Time>
          <Value>0</Value>
        </Keyframe>
      </Keyframes>
    </Uniform>
    <Uniform>
      <UniformName>mainCamY</UniformName>
      <Keyframes>
        <Keyframe>
          <Time>0</Time>
          <Value>0</Value>
        </Keyframe>
        <Keyframe>
          <Time>1.04</Time>
          <Value>0.5</Value>
        </Keyframe>
        <Keyframe>
          <Time>5.42</Time>
          <Value>0</Value>
        </Keyframe>
        <Keyframe>
          <Time>7.01</Time>
          <Value>0</Value>
        </Keyframe>
        <Keyframe>
          <Time>8.94</Time>
          <Value>0.237111434</Value>
        </Keyframe>
        <Keyframe>
          <Time>10.32</Time>
          <Value>0.130434468</Value>
        </Keyframe>
        <Keyframe>
          <Time>12.0073328</Time>
          <Value>0</Value>
        </Keyframe>
        <Keyframe>
          <Time>15.87</Time>
          <Value>0</Value>
        </Keyframe>
        <Keyframe>
          <Time>19.9816685</Time>
          <Value>0</Value>
        </Keyframe>
        <Keyframe>
          <Time>21.63</Time>
          <Value>0</Value>
        </Keyframe>
        <Keyframe>
          <Time>25.0229149</Time>
          <Value>0</Value>
        </Keyframe>
        <Keyframe>
          <Time>29.27</Time>
          <Value>1.5</Value>
        </Keyframe>
        <Keyframe>
          <Time>31.9890022</Time>
          <Value>0</Value>
        </Keyframe>
      </Keyframes>
    </Uniform>
    <Uniform>
      <UniformName>mainCamZ</UniformName>
      <Keyframes>
        <Keyframe>
          <Time>17.42</Time>
          <Value>0</Value>
        </Keyframe>
        <Keyframe>
          <Time>17.675</Time>
          <Value>-0.211794</Value>
        </Keyframe>
        <Keyframe>
          <Time>18.46</Time>
          <Value>-0.8637874</Value>
        </Keyframe>
        <Keyframe>
          <Time>20.43</Time>
          <Value>-2.5</Value>
        </Keyframe>
        <Keyframe>
          <Time>22.84</Time>
          <Value>-0.994354</Value>
        </Keyframe>
        <Keyframe>
          <Time>26.19</Time>
          <Value>0</Value>
        </Keyframe>
        <Keyframe>
          <Time>34.96652</Time>
          <Value>0</Value>
        </Keyframe>
        <Keyframe>
          <Time>39.05</Time>
          <Value>-2.855027</Value>
        </Keyframe>
        <Keyframe>
          <Time>43.6657028</Time>
          <Value>0</Value>
        </Keyframe>
        <Keyframe>
          <Time>52.4106674</Time>
          <Value>0</Value>
        </Keyframe>
        <Keyframe>
          <Time>56.78477</Time>
          <Value>-7.67</Value>
        </Keyframe>
        <Keyframe>
          <Time>61.1235237</Time>
          <Value>0</Value>
        </Keyframe>
        <Keyframe>
          <Time>69.83459</Time>
          <Value>0</Value>
        </Keyframe>
        <Keyframe>
          <Time>74.19217</Time>
          <Value>-5</Value>
        </Keyframe>
        <Keyframe>
          <Time>78.75934</Time>
          <Value>0</Value>
        </Keyframe>
        <Keyframe>
          <Time>87.35059</Time>
          <Value>0</Value>
        </Keyframe>
        <Keyframe>
          <Time>91.69597</Time>
          <Value>-5</Value>
        </Keyframe>
        <Keyframe>
          <Time>96.07234</Time>
          <Value>0</Value>
        </Keyframe>
        <Keyframe>
          <Time>131.3676</Time>
          <Value>0</Value>
        </Keyframe>
        <Keyframe>
          <Time>135.48349</Time>
          <Value>-5</Value>
        </Keyframe>
        <Keyframe>
          <Time>139.7904</Time>
          <Value>0</Value>
        </Keyframe>
        <Keyframe>
          <Time>148.401077</Time>
          <Value>0</Value>
        </Keyframe>
        <Keyframe>
          <Time>154.917572</Time>
          <Value>-6</Value>
        </Keyframe>
        <Keyframe>
          <Time>155.124191</Time>
          <Value>-5.811008</Value>
        </Keyframe>
        <Keyframe>
          <Time>161.477188</Time>
          <Value>0</Value>
        </Keyframe>
        <Keyframe>
          <Time>174.573471</Time>
          <Value>0</Value>
        </Keyframe>
        <Keyframe>
          <Time>181.08754</Time>
          <Value>-5</Value>
        </Keyframe>
        <Keyframe>
          <Time>183.273987</Time>
          <Value>0</Value>
        </Keyframe>
      </Keyframes>
    </Uniform>
    <Uniform>
      <UniformName>rotateCubeX</UniformName>
      <Keyframes>
        <Keyframe>
          <Time>18.46</Time>
          <Value>-15</Value>
        </Keyframe>
        <Keyframe>
          <Time>20.43</Time>
          <Value>25</Value>
        </Keyframe>
        <Keyframe>
          <Time>22.84</Time>
          <Value>9.943541</Value>
        </Keyframe>
        <Keyframe>
          <Time>26.19</Time>
          <Value>0</Value>
        </Keyframe>
        <Keyframe>
          <Time>34.94</Time>
          <Value>0</Value>
        </Keyframe>
        <Keyframe>
          <Time>35.433</Time>
          <Value>-19.85446</Value>
        </Keyframe>
        <Keyframe>
          <Time>36.813</Time>
          <Value>7.841643</Value>
        </Keyframe>
        <Keyframe>
          <Time>38.5003281</Time>
          <Value>0</Value>
        </Keyframe>
        <Keyframe>
          <Time>43.6046257</Time>
          <Value>0</Value>
        </Keyframe>
        <Keyframe>
          <Time>52.63</Time>
          <Value>270</Value>
        </Keyframe>
        <Keyframe>
          <Time>55.763</Time>
          <Value>160.2576</Value>
        </Keyframe>
        <Keyframe>
          <Time>58.482</Time>
          <Value>0</Value>
        </Keyframe>
        <Keyframe>
          <Time>61.08899</Time>
          <Value>90</Value>
        </Keyframe>
        <Keyframe>
          <Time>61.19</Time>
          <Value>90</Value>
        </Keyframe>
        <Keyframe>
          <Time>65.45339</Time>
          <Value>270</Value>
        </Keyframe>
        <Keyframe>
          <Time>69.83459</Time>
          <Value>90</Value>
        </Keyframe>
        <Keyframe>
          <Time>74.41</Time>
          <Value>180</Value>
        </Keyframe>
        <Keyframe>
          <Time>78.97</Time>
          <Value>90</Value>
        </Keyframe>
        <Keyframe>
          <Time>88.4085541</Time>
          <Value>90</Value>
        </Keyframe>
        <Keyframe>
          <Time>90.54202</Time>
          <Value>64.5219</Value>
        </Keyframe>
        <Keyframe>
          <Time>95.9449158</Time>
          <Value>0</Value>
        </Keyframe>
        <Keyframe>
          <Time>97.50668</Time>
          <Value>0</Value>
        </Keyframe>
        <Keyframe>
          <Time>131.122131</Time>
          <Value>0</Value>
        </Keyframe>
        <Keyframe>
          <Time>135.42</Time>
          <Value>90</Value>
        </Keyframe>
        <Keyframe>
          <Time>139.691711</Time>
          <Value>270</Value>
        </Keyframe>
        <Keyframe>
          <Time>148.346359</Time>
          <Value>270</Value>
        </Keyframe>
        <Keyframe>
          <Time>154.898041</Time>
          <Value>270</Value>
        </Keyframe>
        <Keyframe>
          <Time>155.124191</Time>
          <Value>270</Value>
        </Keyframe>
        <Keyframe>
          <Time>161.448334</Time>
          <Value>180</Value>
        </Keyframe>
        <Keyframe>
          <Time>174.551834</Time>
          <Value>180</Value>
        </Keyframe>
        <Keyframe>
          <Time>176.728989</Time>
          <Value>180</Value>
        </Keyframe>
        <Keyframe>
          <Time>178.895462</Time>
          <Value>277.445465</Value>
        </Keyframe>
        <Keyframe>
          <Time>181.104568</Time>
          <Value>180</Value>
        </Keyframe>
        <Keyframe>
          <Time>183.314972</Time>
          <Value>90</Value>
        </Keyframe>
      </Keyframes>
    </Uniform>
    <Uniform>
      <UniformName>rotateCubeY</UniformName>
      <Keyframes>
        <Keyframe>
          <Time>17.42</Time>
          <Value>0</Value>
        </Keyframe>
        <Keyframe>
          <Time>18.46</Time>
          <Value>-31</Value>
        </Keyframe>
        <Keyframe>
          <Time>20.43</Time>
          <Value>21</Value>
        </Keyframe>
        <Keyframe>
          <Time>22.84</Time>
          <Value>105</Value>
        </Keyframe>
        <Keyframe>
          <Time>26.19</Time>
          <Value>90</Value>
        </Keyframe>
        <Keyframe>
          <Time>35.4</Time>
          <Value>90</Value>
        </Keyframe>
        <Keyframe>
          <Time>38.5003281</Time>
          <Value>0</Value>
        </Keyframe>
        <Keyframe>
          <Time>43.6657028</Time>
          <Value>-90</Value>
        </Keyframe>
        <Keyframe>
          <Time>52.01</Time>
          <Value>-90</Value>
        </Keyframe>
        <Keyframe>
          <Time>52.63</Time>
          <Value>-90</Value>
        </Keyframe>
        <Keyframe>
          <Time>55.763</Time>
          <Value>128.956</Value>
        </Keyframe>
        <Keyframe>
          <Time>58.482</Time>
          <Value>0</Value>
        </Keyframe>
        <Keyframe>
          <Time>61.08899</Time>
          <Value>0</Value>
        </Keyframe>
        <Keyframe>
          <Time>61.19</Time>
          <Value>0</Value>
        </Keyframe>
        <Keyframe>
          <Time>69.83459</Time>
          <Value>0</Value>
        </Keyframe>
        <Keyframe>
          <Time>74.41</Time>
          <Value>90</Value>
        </Keyframe>
        <Keyframe>
          <Time>78.97</Time>
          <Value>0</Value>
        </Keyframe>
        <Keyframe>
          <Time>87.9011154</Time>
          <Value>0</Value>
        </Keyframe>
        <Keyframe>
          <Time>88.4085541</Time>
          <Value>0</Value>
        </Keyframe>
        <Keyframe>
          <Time>88.86622</Time>
          <Value>10.9309521</Value>
        </Keyframe>
        <Keyframe>
          <Time>95.9449158</Time>
          <Value>180</Value>
        </Keyframe>
        <Keyframe>
          <Time>103.253036</Time>
          <Value>180</Value>
        </Keyframe>
        <Keyframe>
          <Time>131.122131</Time>
          <Value>180</Value>
        </Keyframe>
        <Keyframe>
          <Time>139.691711</Time>
          <Value>0</Value>
        </Keyframe>
        <Keyframe>
          <Time>140.693787</Time>
          <Value>0</Value>
        </Keyframe>
        <Keyframe>
          <Time>148.359253</Time>
          <Value>0</Value>
        </Keyframe>
        <Keyframe>
          <Time>155.124191</Time>
          <Value>300</Value>
        </Keyframe>
        <Keyframe>
          <Time>161.448334</Time>
          <Value>90</Value>
        </Keyframe>
        <Keyframe>
          <Time>174.551834</Time>
          <Value>90</Value>
        </Keyframe>
        <Keyframe>
          <Time>176.728989</Time>
          <Value>125.686913</Value>
        </Keyframe>
        <Keyframe>
          <Time>178.895462</Time>
          <Value>-26.4476013</Value>
        </Keyframe>
        <Keyframe>
          <Time>181.104568</Time>
          <Value>90</Value>
        </Keyframe>
        <Keyframe>
          <Time>183.314972</Time>
          <Value>180</Value>
        </Keyframe>
      </Keyframes>
    </Uniform>
    <Uniform>
      <UniformName>rotateCubeZ</UniformName>
      <Keyframes>
        <Keyframe>
          <Time>17.42</Time>
          <Value>0</Value>
        </Keyframe>
        <Keyframe>
          <Time>18.46</Time>
          <Value>15</Value>
        </Keyframe>
        <Keyframe>
          <Time>20.43</Time>
          <Value>21.19824</Value>
        </Keyframe>
        <Keyframe>
          <Time>22.84</Time>
          <Value>2.38645</Value>
        </Keyframe>
        <Keyframe>
          <Time>26.19</Time>
          <Value>0</Value>
        </Keyframe>
        <Keyframe>
          <Time>26.36</Time>
          <Value>19.81379</Value>
        </Keyframe>
        <Keyframe>
          <Time>29.42733</Time>
          <Value>0</Value>
        </Keyframe>
        <Keyframe>
          <Time>37.0386658</Time>
          <Value>-180</Value>
        </Keyframe>
        <Keyframe>
          <Time>43.61429</Time>
          <Value>0</Value>
        </Keyframe>
        <Keyframe>
          <Time>61.29</Time>
          <Value>0</Value>
        </Keyframe>
        <Keyframe>
          <Time>69.8625946</Time>
          <Value>0</Value>
        </Keyframe>
        <Keyframe>
          <Time>74.41</Time>
          <Value>176.541672</Value>
        </Keyframe>
        <Keyframe>
          <Time>78.97</Time>
          <Value>0</Value>
        </Keyframe>
        <Keyframe>
          <Time>88.4085541</Time>
          <Value>0</Value>
        </Keyframe>
        <Keyframe>
          <Time>90.54202</Time>
          <Value>349.247559</Value>
        </Keyframe>
        <Keyframe>
          <Time>91.70728</Time>
          <Value>540</Value>
        </Keyframe>
        <Keyframe>
          <Time>95.9449158</Time>
          <Value>0</Value>
        </Keyframe>
        <Keyframe>
          <Time>97.50668</Time>
          <Value>0</Value>
        </Keyframe>
        <Keyframe>
          <Time>131.122131</Time>
          <Value>0</Value>
        </Keyframe>
        <Keyframe>
          <Time>135.42</Time>
          <Value>-90</Value>
        </Keyframe>
        <Keyframe>
          <Time>139.691711</Time>
          <Value>0</Value>
        </Keyframe>
        <Keyframe>
          <Time>148.346359</Time>
          <Value>0</Value>
        </Keyframe>
        <Keyframe>
          <Time>154.898041</Time>
          <Value>270</Value>
        </Keyframe>
        <Keyframe>
          <Time>161.448334</Time>
          <Value>0</Value>
        </Keyframe>
        <Keyframe>
          <Time>174.551834</Time>
          <Value>180</Value>
        </Keyframe>
        <Keyframe>
          <Time>183.314972</Time>
          <Value>0</Value>
        </Keyframe>
      </Keyframes>
    </Uniform>
    <Uniform>
      <UniformName>spinCube</UniformName>
      <Keyframes>
        <Keyframe>
          <Time>165.805313</Time>
          <Value>500</Value>
        </Keyframe>
        <Keyframe>
          <Time>165.816925</Time>
          <Value>500</Value>
        </Keyframe>
        <Keyframe>
          <Time>168.0412</Time>
          <Value>100</Value>
        </Keyframe>
        <Keyframe>
          <Time>170.213364</Time>
          <Value>100</Value>
        </Keyframe>
        <Keyframe>
          <Time>171.600143</Time>
          <Value>138.985062</Value>
        </Keyframe>
        <Keyframe>
          <Time>172.344574</Time>
          <Value>56.2826538</Value>
        </Keyframe>
        <Keyframe>
          <Time>172.353561</Time>
          <Value>55.2842</Value>
        </Keyframe>
        <Keyframe>
          <Time>172.372635</Time>
          <Value>53.1652374</Value>
        </Keyframe>
        <Keyframe>
          <Time>172.4056</Time>
          <Value>49.5036621</Value>
        </Keyframe>
        <Keyframe>
          <Time>173.043671</Time>
          <Value>140.592957</Value>
        </Keyframe>
        <Keyframe>
          <Time>174.523071</Time>
          <Value>351.786316</Value>
        </Keyframe>
        <Keyframe>
          <Time>174.527847</Time>
          <Value>351.786316</Value>
        </Keyframe>
        <Keyframe>
          <Time>174.776825</Time>
          <Value>164.462433</Value>
        </Keyframe>
        <Keyframe>
          <Time>177.581879</Time>
          <Value>164.462433</Value>
        </Keyframe>
      </Keyframes>
    </Uniform>
    <Uniform>
      <UniformName>move</UniformName>
      <Keyframes>
        <Keyframe>
          <Time>165.805313</Time>
          <Value>0</Value>
        </Keyframe>
        <Keyframe>
          <Time>167.556061</Time>
          <Value>1</Value>
        </Keyframe>
        <Keyframe>
          <Time>168.0539</Time>
          <Value>4</Value>
        </Keyframe>
        <Keyframe>
          <Time>170.179932</Time>
          <Value>2</Value>
        </Keyframe>
        <Keyframe>
          <Time>171.600143</Time>
          <Value>1</Value>
        </Keyframe>
        <Keyframe>
          <Time>172.353561</Time>
          <Value>4</Value>
        </Keyframe>
        <Keyframe>
          <Time>173.043671</Time>
          <Value>1</Value>
        </Keyframe>
        <Keyframe>
          <Time>174.527847</Time>
          <Value>0</Value>
        </Keyframe>
        <Keyframe>
          <Time>177.581879</Time>
          <Value>1</Value>
        </Keyframe>
      </Keyframes>
    </Uniform>
    <Uniform>
      <UniformName>spiralRot</UniformName>
      <Keyframes>
        <Keyframe>
          <Time>36.9989662</Time>
          <Value>180</Value>
        </Keyframe>
        <Keyframe>
          <Time>42.7979736</Time>
          <Value>60</Value>
        </Keyframe>
        <Keyframe>
          <Time>43.68327</Time>
          <Value>20</Value>
        </Keyframe>
        <Keyframe>
          <Time>45.40531</Time>
          <Value>45</Value>
        </Keyframe>
        <Keyframe>
          <Time>45.8247</Time>
          <Value>120</Value>
        </Keyframe>
        <Keyframe>
          <Time>47.7356834</Time>
          <Value>95</Value>
        </Keyframe>
        <Keyframe>
          <Time>48.0329857</Time>
          <Value>15</Value>
        </Keyframe>
        <Keyframe>
          <Time>49.9503365</Time>
          <Value>45</Value>
        </Keyframe>
        <Keyframe>
          <Time>50.20063</Time>
          <Value>125</Value>
        </Keyframe>
        <Keyframe>
          <Time>52.3684044</Time>
          <Value>160</Value>
        </Keyframe>
      </Keyframes>
    </Uniform>
    <Uniform>
      <UniformName>uMoveY</UniformName>
      <Keyframes>
        <Keyframe>
          <Time>0</Time>
          <Value>1</Value>
        </Keyframe>
        <Keyframe>
          <Time>10.8058605</Time>
          <Value>1</Value>
        </Keyframe>
        <Keyframe>
          <Time>11.8131866</Time>
          <Value>2</Value>
        </Keyframe>
      </Keyframes>
    </Uniform>
    <Uniform>
      <UniformName>uRepeatY</UniformName>
      <Keyframes>
        <Keyframe>
          <Time>0</Time>
          <Value>1</Value>
        </Keyframe>
        <Keyframe>
          <Time>10.8058605</Time>
          <Value>1</Value>
        </Keyframe>
        <Keyframe>
          <Time>11.8131866</Time>
          <Value>5</Value>
        </Keyframe>
      </Keyframes>
    </Uniform>
    <Uniform>
      <UniformName>uMoveX</UniformName>
      <Keyframes>
        <Keyframe>
          <Time>0</Time>
          <Value>1</Value>
        </Keyframe>
        <Keyframe>
          <Time>3.296704</Time>
          <Value>1</Value>
        </Keyframe>
        <Keyframe>
          <Time>4.212454</Time>
          <Value>2</Value>
        </Keyframe>
      </Keyframes>
    </Uniform>
    <Uniform>
      <UniformName>uRepeatZ</UniformName>
      <Keyframes>
        <Keyframe>
          <Time>0</Time>
          <Value>1</Value>
        </Keyframe>
        <Keyframe>
          <Time>5.6776557</Time>
          <Value>1</Value>
        </Keyframe>
        <Keyframe>
          <Time>6.227106</Time>
          <Value>5</Value>
        </Keyframe>
      </Keyframes>
    </Uniform>
    <Uniform>
      <UniformName>uRepeatX</UniformName>
      <Keyframes>
        <Keyframe>
          <Time>0</Time>
          <Value>1</Value>
        </Keyframe>
        <Keyframe>
          <Time>3.205128</Time>
          <Value>1</Value>
        </Keyframe>
        <Keyframe>
          <Time>3.296704</Time>
          <Value>5</Value>
        </Keyframe>
      </Keyframes>
    </Uniform>
    <Uniform>
      <UniformName>uMoveZ</UniformName>
      <Keyframes>
        <Keyframe>
          <Time>0</Time>
          <Value>1</Value>
        </Keyframe>
        <Keyframe>
          <Time>5.6776557</Time>
          <Value>1</Value>
        </Keyframe>
        <Keyframe>
          <Time>6.227106</Time>
          <Value>2</Value>
        </Keyframe>
      </Keyframes>
    </Uniform>
    <Uniform>
      <UniformName>uScale</UniformName>
      <Keyframes>
        <Keyframe>
          <Time>0</Time>
          <Value>0</Value>
        </Keyframe>
        <Keyframe>
          <Time>1.007326</Time>
          <Value>0</Value>
        </Keyframe>
        <Keyframe>
          <Time>1.55677652</Time>
          <Value>1</Value>
        </Keyframe>
      </Keyframes>
    </Uniform>
    <Uniform>
      <UniformName>uCameraZ</UniformName>
      <Keyframes>
        <Keyframe>
          <Time>0.255000025</Time>
          <Value>0</Value>
        </Keyframe>
        <Keyframe>
          <Time>9.086</Time>
          <Value>-4.49825</Value>
        </Keyframe>
        <Keyframe>
          <Time>23.56575</Time>
          <Value>0</Value>
        </Keyframe>
        <Keyframe>
          <Time>31.1962738</Time>
          <Value>-5</Value>
        </Keyframe>
        <Keyframe>
          <Time>38.20116</Time>
          <Value>0</Value>
        </Keyframe>
        <Keyframe>
          <Time>43.7088661</Time>
          <Value>0</Value>
        </Keyframe>
      </Keyframes>
    </Uniform>
    <Uniform>
      <UniformName>uStartRotationTime</UniformName>
      <Keyframes>
        <Keyframe>
          <Time>24.17795</Time>
          <Value>24.17795</Value>
        </Keyframe>
        <Keyframe>
          <Time>43.7088661</Time>
          <Value>24.17795</Value>
        </Keyframe>
      </Keyframes>
    </Uniform>
    <Uniform>
      <UniformName>iCamRotX</UniformName>
      <Keyframes>
        <Keyframe>
          <Time>0</Time>
          <Value>24.09</Value>
        </Keyframe>
        <Keyframe>
          <Time>4.54637146</Time>
          <Value>45</Value>
        </Keyframe>
        <Keyframe>
          <Time>8.4145565</Time>
          <Value>24.09</Value>
        </Keyframe>
        <Keyframe>
          <Time>24.0856972</Time>
          <Value>45</Value>
        </Keyframe>
        <Keyframe>
          <Time>29.160759</Time>
          <Value>29.6032944</Value>
        </Keyframe>
        <Keyframe>
          <Time>35.9595375</Time>
          <Value>36.9891472</Value>
        </Keyframe>
        <Keyframe>
          <Time>183.253281</Time>
          <Value>24</Value>
        </Keyframe>
        <Keyframe>
          <Time>185.445328</Time>
          <Value>45</Value>
        </Keyframe>
        <Keyframe>
          <Time>187.598221</Time>
          <Value>24</Value>
        </Keyframe>
        <Keyframe>
          <Time>189.800156</Time>
          <Value>36.9891472</Value>
        </Keyframe>
      </Keyframes>
    </Uniform>
    <Uniform>
      <UniformName>iCamPosY</UniformName>
      <Keyframes>
        <Keyframe>
          <Time>0</Time>
          <Value>0</Value>
        </Keyframe>
        <Keyframe>
          <Time>119.44</Time>
          <Value>0</Value>
        </Keyframe>
        <Keyframe>
          <Time>143.5257</Time>
          <Value>-40</Value>
        </Keyframe>
        <Keyframe>
          <Time>176.769928</Time>
          <Value>-10</Value>
        </Keyframe>
        <Keyframe>
          <Time>178.952835</Time>
          <Value>-10</Value>
        </Keyframe>
        <Keyframe>
          <Time>189.800156</Time>
          <Value>-20</Value>
        </Keyframe>
        <Keyframe>
          <Time>192.175491</Time>
          <Value>-22.5</Value>
        </Keyframe>
      </Keyframes>
    </Uniform>
    <Uniform>
      <UniformName>iCamRotY</UniformName>
      <Keyframes>
        <Keyframe>
          <Time>0</Time>
          <Value>24.09</Value>
        </Keyframe>
        <Keyframe>
          <Time>119.44</Time>
          <Value>24.09</Value>
        </Keyframe>
        <Keyframe>
          <Time>123.986374</Time>
          <Value>24.09</Value>
        </Keyframe>
        <Keyframe>
          <Time>127.854553</Time>
          <Value>24.09</Value>
        </Keyframe>
        <Keyframe>
          <Time>143.5257</Time>
          <Value>24.09</Value>
        </Keyframe>
        <Keyframe>
          <Time>148.600754</Time>
          <Value>29.60329</Value>
        </Keyframe>
        <Keyframe>
          <Time>155.399536</Time>
          <Value>36.98915</Value>
        </Keyframe>
        <Keyframe>
          <Time>171.978775</Time>
          <Value>55</Value>
        </Keyframe>
        <Keyframe>
          <Time>178.295715</Time>
          <Value>24</Value>
        </Keyframe>
        <Keyframe>
          <Time>189.800156</Time>
          <Value>55</Value>
        </Keyframe>
      </Keyframes>
    </Uniform>
    <Uniform>
      <UniformName>iCamPosZ</UniformName>
      <Keyframes>
        <Keyframe>
          <Time>0</Time>
          <Value>0</Value>
        </Keyframe>
        <Keyframe>
          <Time>119.44</Time>
          <Value>0</Value>
        </Keyframe>
        <Keyframe>
          <Time>143.5257</Time>
          <Value>50</Value>
        </Keyframe>
        <Keyframe>
          <Time>183.253281</Time>
          <Value>0</Value>
        </Keyframe>
        <Keyframe>
          <Time>189.800156</Time>
          <Value>20</Value>
        </Keyframe>
        <Keyframe>
          <Time>192.175491</Time>
          <Value>30</Value>
        </Keyframe>
      </Keyframes>
    </Uniform>
    <Uniform>
      <UniformName>iCamRotZ</UniformName>
      <Keyframes>
        <Keyframe>
          <Time>0</Time>
          <Value>0</Value>
        </Keyframe>
        <Keyframe>
          <Time>24.0856972</Time>
          <Value>0</Value>
        </Keyframe>
      </Keyframes>
    </Uniform>
    <Uniform>
      <UniformName>rotatePX</UniformName>
      <Keyframes>
        <Keyframe>
          <Time>123.306</Time>
          <Value>240</Value>
        </Keyframe>
        <Keyframe>
          <Time>127.546371</Time>
          <Value>253.9073</Value>
        </Keyframe>
        <Keyframe>
          <Time>131.4146</Time>
          <Value>265.7401</Value>
        </Keyframe>
        <Keyframe>
          <Time>152.1608</Time>
          <Value>329.2026</Value>
        </Keyframe>
        <Keyframe>
          <Time>158.9595</Time>
          <Value>350</Value>
        </Keyframe>
        <Keyframe>
          <Time>180.8557</Time>
          <Value>240</Value>
        </Keyframe>
        <Keyframe>
          <Time>189.800156</Time>
          <Value>350</Value>
        </Keyframe>
      </Keyframes>
    </Uniform>
    <Uniform>
      <UniformName>rotatePY</UniformName>
      <Keyframes>
        <Keyframe>
          <Time>153.306</Time>
          <Value>120</Value>
        </Keyframe>
        <Keyframe>
          <Time>157.5464</Time>
          <Value>126.9537</Value>
        </Keyframe>
        <Keyframe>
          <Time>161.4146</Time>
          <Value>132.87</Value>
        </Keyframe>
        <Keyframe>
          <Time>182.9595</Time>
          <Value>120</Value>
        </Keyframe>
        <Keyframe>
          <Time>183.253281</Time>
          <Value>120</Value>
        </Keyframe>
        <Keyframe>
          <Time>210.8557</Time>
          <Value>140</Value>
        </Keyframe>
      </Keyframes>
    </Uniform>
    <Uniform>
      <UniformName>rotatePZ</UniformName>
      <Keyframes>
        <Keyframe>
          <Time>123.306</Time>
          <Value>0</Value>
        </Keyframe>
        <Keyframe>
          <Time>127.546371</Time>
          <Value>5.689359</Value>
        </Keyframe>
        <Keyframe>
          <Time>131.4146</Time>
          <Value>10.53003</Value>
        </Keyframe>
        <Keyframe>
          <Time>152.1608</Time>
          <Value>36.49196</Value>
        </Keyframe>
        <Keyframe>
          <Time>158.9595</Time>
          <Value>45</Value>
        </Keyframe>
        <Keyframe>
          <Time>180.8557</Time>
          <Value>0</Value>
        </Keyframe>
        <Keyframe>
          <Time>189.800156</Time>
          <Value>15</Value>
        </Keyframe>
      </Keyframes>
    </Uniform>
    <Uniform>
      <UniformName>interpolate</UniformName>
      <Keyframes>
        <Keyframe>
          <Time>0</Time>
          <Value>0</Value>
        </Keyframe>
        <Keyframe>
          <Time>43.7088661</Time>
          <Value>11.3056154</Value>
        </Keyframe>
        <Keyframe>
          <Time>116.062859</Time>
          <Value>23.2724514</Value>
        </Keyframe>
        <Keyframe>
          <Time>193.306</Time>
          <Value>50</Value>
        </Keyframe>
      </Keyframes>
    </Uniform>
    <Uniform>
      <UniformName>divide</UniformName>
      <Keyframes>
        <Keyframe>
          <Time>0</Time>
          <Value>1</Value>
        </Keyframe>
        <Keyframe>
          <Time>21.7637634</Time>
          <Value>0.49560982</Value>
        </Keyframe>
        <Keyframe>
          <Time>30.2040634</Time>
          <Value>0.3</Value>
        </Keyframe>
        <Keyframe>
          <Time>34.82576</Time>
          <Value>0.3</Value>
        </Keyframe>
        <Keyframe>
          <Time>36.2631874</Time>
          <Value>0.3000043</Value>
        </Keyframe>
        <Keyframe>
          <Time>165.816925</Time>
          <Value>0.300391555</Value>
        </Keyframe>
        <Keyframe>
          <Time>166.0506</Time>
          <Value>0.3</Value>
        </Keyframe>
        <Keyframe>
          <Time>168.0412</Time>
          <Value>0.351124555</Value>
        </Keyframe>
        <Keyframe>
          <Time>170.213364</Time>
          <Value>0.406912237</Value>
        </Keyframe>
        <Keyframe>
          <Time>172.4056</Time>
          <Value>0.463215262</Value>
        </Keyframe>
        <Keyframe>
          <Time>174.523071</Time>
          <Value>0.5175984</Value>
        </Keyframe>
        <Keyframe>
          <Time>193.306</Time>
          <Value>1</Value>
        </Keyframe>
      </Keyframes>
    </Uniform>
    <Uniform>
      <UniformName>rep</UniformName>
      <Keyframes>
        <Keyframe>
          <Time>0</Time>
          <Value>5</Value>
        </Keyframe>
        <Keyframe>
          <Time>8.63</Time>
          <Value>5</Value>
        </Keyframe>
        <Keyframe>
          <Time>17.39918</Time>
          <Value>5</Value>
        </Keyframe>
        <Keyframe>
          <Time>21.7637634</Time>
          <Value>6.0165906</Value>
        </Keyframe>
        <Keyframe>
          <Time>30.2792435</Time>
          <Value>8</Value>
        </Keyframe>
        <Keyframe>
          <Time>30.6042786</Time>
          <Value>2.4</Value>
        </Keyframe>
        <Keyframe>
          <Time>32.3739</Time>
          <Value>2.4</Value>
        </Keyframe>
        <Keyframe>
          <Time>32.7401276</Time>
          <Value>5</Value>
        </Keyframe>
        <Keyframe>
          <Time>43.0723152</Time>
          <Value>5</Value>
        </Keyframe>
        <Keyframe>
          <Time>52.349865</Time>
          <Value>7.029911</Value>
        </Keyframe>
        <Keyframe>
          <Time>56.78358</Time>
          <Value>8</Value>
        </Keyframe>
        <Keyframe>
          <Time>61.15182</Time>
          <Value>4</Value>
        </Keyframe>
        <Keyframe>
          <Time>69.83521</Time>
          <Value>5</Value>
        </Keyframe>
        <Keyframe>
          <Time>78.59759</Time>
          <Value>7</Value>
        </Keyframe>
        <Keyframe>
          <Time>89.87084</Time>
          <Value>6.17774248</Value>
        </Keyframe>
        <Keyframe>
          <Time>92.60201</Time>
          <Value>8.440047</Value>
        </Keyframe>
        <Keyframe>
          <Time>125.32</Time>
          <Value>6.513938</Value>
        </Keyframe>
        <Keyframe>
          <Time>130.033981</Time>
          <Value>6.236426</Value>
        </Keyframe>
        <Keyframe>
          <Time>130.962372</Time>
          <Value>6.18177128</Value>
        </Keyframe>
        <Keyframe>
          <Time>133.11319</Time>
          <Value>6.05515242</Value>
        </Keyframe>
        <Keyframe>
          <Time>133.291321</Time>
          <Value>6.044666</Value>
        </Keyframe>
        <Keyframe>
          <Time>137.608337</Time>
          <Value>8.440047</Value>
        </Keyframe>
        <Keyframe>
          <Time>179.508347</Time>
          <Value>8.440047</Value>
        </Keyframe>
        <Keyframe>
          <Time>180.208389</Time>
          <Value>8.440047</Value>
        </Keyframe>
        <Keyframe>
          <Time>187.308823</Time>
          <Value>8.440047</Value>
        </Keyframe>
      </Keyframes>
    </Uniform>
    <Uniform>
      <UniformName>tresh</UniformName>
      <Keyframes>
        <Keyframe>
          <Time>0</Time>
          <Value>33</Value>
        </Keyframe>
        <Keyframe>
          <Time>21.7637634</Time>
          <Value>85.78762</Value>
        </Keyframe>
        <Keyframe>
          <Time>26.1987171</Time>
          <Value>85.4172058</Value>
        </Keyframe>
        <Keyframe>
          <Time>32.698513</Time>
          <Value>66</Value>
        </Keyframe>
        <Keyframe>
          <Time>38.9407921</Time>
          <Value>75.217</Value>
        </Keyframe>
        <Keyframe>
          <Time>52.349865</Time>
          <Value>95.0161</Value>
        </Keyframe>
        <Keyframe>
          <Time>76.04295</Time>
          <Value>130</Value>
        </Keyframe>
        <Keyframe>
          <Time>125.32</Time>
          <Value>75</Value>
        </Keyframe>
        <Keyframe>
          <Time>134.620041</Time>
          <Value>50</Value>
        </Keyframe>
        <Keyframe>
          <Time>161.736542</Time>
          <Value>63.268837</Value>
        </Keyframe>
        <Keyframe>
          <Time>166.016037</Time>
          <Value>39.3</Value>
        </Keyframe>
      </Keyframes>
    </Uniform>
    <Uniform>
      <UniformName>p45Translation</UniformName>
      <Keyframes>
        <Keyframe>
          <Time>0</Time>
          <Value>3.5</Value>
        </Keyframe>
        <Keyframe>
          <Time>60.75</Time>
          <Value>3.5</Value>
        </Keyframe>
        <Keyframe>
          <Time>61.15343</Time>
          <Value>7</Value>
        </Keyframe>
        <Keyframe>
          <Time>69.77</Time>
          <Value>7</Value>
        </Keyframe>
        <Keyframe>
          <Time>86.20164</Time>
          <Value>7</Value>
        </Keyframe>
        <Keyframe>
          <Time>86.30164</Time>
          <Value>3.5</Value>
        </Keyframe>
        <Keyframe>
          <Time>100</Time>
          <Value>3.5</Value>
        </Keyframe>
      </Keyframes>
    </Uniform>
    <Uniform>
      <UniformName>p4Rotation</UniformName>
      <Keyframes>
        <Keyframe>
          <Time>4.2</Time>
          <Value>90</Value>
        </Keyframe>
        <Keyframe>
          <Time>65.48</Time>
          <Value>90</Value>
        </Keyframe>
        <Keyframe>
          <Time>65.59</Time>
          <Value>-270</Value>
        </Keyframe>
        <Keyframe>
          <Time>66.22</Time>
          <Value>-270</Value>
        </Keyframe>
        <Keyframe>
          <Time>66.4</Time>
          <Value>-90</Value>
        </Keyframe>
        <Keyframe>
          <Time>66.44</Time>
          <Value>-90</Value>
        </Keyframe>
        <Keyframe>
          <Time>66.69</Time>
          <Value>90</Value>
        </Keyframe>
        <Keyframe>
          <Time>67.5156</Time>
          <Value>90</Value>
        </Keyframe>
        <Keyframe>
          <Time>67.6956</Time>
          <Value>-90</Value>
        </Keyframe>
        <Keyframe>
          <Time>67.7356</Time>
          <Value>-90</Value>
        </Keyframe>
        <Keyframe>
          <Time>67.8556</Time>
          <Value>-270</Value>
        </Keyframe>
        <Keyframe>
          <Time>67.9556</Time>
          <Value>-270</Value>
        </Keyframe>
        <Keyframe>
          <Time>68.1556</Time>
          <Value>0</Value>
        </Keyframe>
        <Keyframe>
          <Time>68.2</Time>
          <Value>90</Value>
        </Keyframe>
        <Keyframe>
          <Time>68.32</Time>
          <Value>90</Value>
        </Keyframe>
        <Keyframe>
          <Time>68.42</Time>
          <Value>-90</Value>
        </Keyframe>
        <Keyframe>
          <Time>68.62</Time>
          <Value>90</Value>
        </Keyframe>
        <Keyframe>
          <Time>72.97</Time>
          <Value>90</Value>
        </Keyframe>
        <Keyframe>
          <Time>74.08</Time>
          <Value>90</Value>
        </Keyframe>
        <Keyframe>
          <Time>74.19</Time>
          <Value>-270</Value>
        </Keyframe>
        <Keyframe>
          <Time>74.82</Time>
          <Value>-270</Value>
        </Keyframe>
        <Keyframe>
          <Time>75</Time>
          <Value>-90</Value>
        </Keyframe>
        <Keyframe>
          <Time>75.04</Time>
          <Value>-90</Value>
        </Keyframe>
        <Keyframe>
          <Time>75.29</Time>
          <Value>90</Value>
        </Keyframe>
        <Keyframe>
          <Time>76.1156</Time>
          <Value>90</Value>
        </Keyframe>
        <Keyframe>
          <Time>76.2956</Time>
          <Value>-90</Value>
        </Keyframe>
        <Keyframe>
          <Time>76.3356</Time>
          <Value>-90</Value>
        </Keyframe>
        <Keyframe>
          <Time>76.4556</Time>
          <Value>-270</Value>
        </Keyframe>
        <Keyframe>
          <Time>76.5556</Time>
          <Value>-270</Value>
        </Keyframe>
        <Keyframe>
          <Time>76.7556</Time>
          <Value>0</Value>
        </Keyframe>
        <Keyframe>
          <Time>76.8</Time>
          <Value>-90</Value>
        </Keyframe>
        <Keyframe>
          <Time>76.92</Time>
          <Value>90</Value>
        </Keyframe>
        <Keyframe>
          <Time>77.02</Time>
          <Value>90</Value>
        </Keyframe>
        <Keyframe>
          <Time>77.22</Time>
          <Value>-90</Value>
        </Keyframe>
        <Keyframe>
          <Time>77.27</Time>
          <Value>90</Value>
        </Keyframe>
        <Keyframe>
          <Time>78.38</Time>
          <Value>90</Value>
        </Keyframe>
        <Keyframe>
          <Time>78.49</Time>
          <Value>-270</Value>
        </Keyframe>
        <Keyframe>
          <Time>79.12</Time>
          <Value>-270</Value>
        </Keyframe>
        <Keyframe>
          <Time>79.3</Time>
          <Value>-90</Value>
        </Keyframe>
        <Keyframe>
          <Time>79.34</Time>
          <Value>-90</Value>
        </Keyframe>
        <Keyframe>
          <Time>79.59</Time>
          <Value>90</Value>
        </Keyframe>
        <Keyframe>
          <Time>80.4156</Time>
          <Value>90</Value>
        </Keyframe>
        <Keyframe>
          <Time>80.5956</Time>
          <Value>-90</Value>
        </Keyframe>
        <Keyframe>
          <Time>80.6356</Time>
          <Value>-90</Value>
        </Keyframe>
        <Keyframe>
          <Time>80.7556</Time>
          <Value>-270</Value>
        </Keyframe>
        <Keyframe>
          <Time>80.8556</Time>
          <Value>-270</Value>
        </Keyframe>
        <Keyframe>
          <Time>81.0556</Time>
          <Value>0</Value>
        </Keyframe>
        <Keyframe>
          <Time>81.1</Time>
          <Value>-90</Value>
        </Keyframe>
        <Keyframe>
          <Time>81.22</Time>
          <Value>90</Value>
        </Keyframe>
        <Keyframe>
          <Time>81.32</Time>
          <Value>90</Value>
        </Keyframe>
        <Keyframe>
          <Time>81.52</Time>
          <Value>-90</Value>
        </Keyframe>
        <Keyframe>
          <Time>81.57</Time>
          <Value>90</Value>
        </Keyframe>
        <Keyframe>
          <Time>81.67</Time>
          <Value>90</Value>
        </Keyframe>
        <Keyframe>
          <Time>82.78</Time>
          <Value>90</Value>
        </Keyframe>
        <Keyframe>
          <Time>82.89</Time>
          <Value>-270</Value>
        </Keyframe>
        <Keyframe>
          <Time>83.52</Time>
          <Value>-270</Value>
        </Keyframe>
        <Keyframe>
          <Time>83.7</Time>
          <Value>-90</Value>
        </Keyframe>
        <Keyframe>
          <Time>83.74</Time>
          <Value>-90</Value>
        </Keyframe>
        <Keyframe>
          <Time>83.99</Time>
          <Value>90</Value>
        </Keyframe>
        <Keyframe>
          <Time>84.8156</Time>
          <Value>90</Value>
        </Keyframe>
        <Keyframe>
          <Time>84.9956</Time>
          <Value>-90</Value>
        </Keyframe>
        <Keyframe>
          <Time>85.0356</Time>
          <Value>-90</Value>
        </Keyframe>
        <Keyframe>
          <Time>85.1556</Time>
          <Value>-270</Value>
        </Keyframe>
        <Keyframe>
          <Time>85.2556</Time>
          <Value>-270</Value>
        </Keyframe>
        <Keyframe>
          <Time>85.4556</Time>
          <Value>0</Value>
        </Keyframe>
        <Keyframe>
          <Time>85.5</Time>
          <Value>-90</Value>
        </Keyframe>
        <Keyframe>
          <Time>85.62</Time>
          <Value>90</Value>
        </Keyframe>
        <Keyframe>
          <Time>85.72</Time>
          <Value>90</Value>
        </Keyframe>
        <Keyframe>
          <Time>85.92</Time>
          <Value>-90</Value>
        </Keyframe>
        <Keyframe>
          <Time>85.97</Time>
          <Value>90</Value>
        </Keyframe>
      </Keyframes>
    </Uniform>
    <Uniform>
      <UniformName>p3Rotation</UniformName>
      <Keyframes>
        <Keyframe>
          <Time>8.5</Time>
          <Value>0</Value>
        </Keyframe>
        <Keyframe>
          <Time>69.78</Time>
          <Value>0</Value>
        </Keyframe>
        <Keyframe>
          <Time>69.89</Time>
          <Value>-270</Value>
        </Keyframe>
        <Keyframe>
          <Time>70.52</Time>
          <Value>-270</Value>
        </Keyframe>
        <Keyframe>
          <Time>70.7</Time>
          <Value>-90</Value>
        </Keyframe>
        <Keyframe>
          <Time>70.74</Time>
          <Value>-90</Value>
        </Keyframe>
        <Keyframe>
          <Time>70.99</Time>
          <Value>90</Value>
        </Keyframe>
        <Keyframe>
          <Time>71.8156</Time>
          <Value>90</Value>
        </Keyframe>
        <Keyframe>
          <Time>71.9956</Time>
          <Value>-90</Value>
        </Keyframe>
        <Keyframe>
          <Time>72.0356</Time>
          <Value>-90</Value>
        </Keyframe>
        <Keyframe>
          <Time>72.1556</Time>
          <Value>-270</Value>
        </Keyframe>
        <Keyframe>
          <Time>72.2556</Time>
          <Value>-270</Value>
        </Keyframe>
        <Keyframe>
          <Time>72.4556</Time>
          <Value>0</Value>
        </Keyframe>
        <Keyframe>
          <Time>72.5</Time>
          <Value>-90</Value>
        </Keyframe>
        <Keyframe>
          <Time>72.62</Time>
          <Value>90</Value>
        </Keyframe>
        <Keyframe>
          <Time>72.72</Time>
          <Value>90</Value>
        </Keyframe>
        <Keyframe>
          <Time>72.92</Time>
          <Value>-90</Value>
        </Keyframe>
        <Keyframe>
          <Time>72.97</Time>
          <Value>0</Value>
        </Keyframe>
        <Keyframe>
          <Time>74.08</Time>
          <Value>90</Value>
        </Keyframe>
        <Keyframe>
          <Time>74.19</Time>
          <Value>-270</Value>
        </Keyframe>
        <Keyframe>
          <Time>74.82</Time>
          <Value>-270</Value>
        </Keyframe>
        <Keyframe>
          <Time>75</Time>
          <Value>-90</Value>
        </Keyframe>
        <Keyframe>
          <Time>75.04</Time>
          <Value>-90</Value>
        </Keyframe>
        <Keyframe>
          <Time>75.29</Time>
          <Value>90</Value>
        </Keyframe>
        <Keyframe>
          <Time>76.1156</Time>
          <Value>90</Value>
        </Keyframe>
        <Keyframe>
          <Time>76.2956</Time>
          <Value>-90</Value>
        </Keyframe>
        <Keyframe>
          <Time>76.3356</Time>
          <Value>-90</Value>
        </Keyframe>
        <Keyframe>
          <Time>76.4556</Time>
          <Value>-270</Value>
        </Keyframe>
        <Keyframe>
          <Time>76.5556</Time>
          <Value>-270</Value>
        </Keyframe>
        <Keyframe>
          <Time>76.7556</Time>
          <Value>0</Value>
        </Keyframe>
        <Keyframe>
          <Time>76.8</Time>
          <Value>-90</Value>
        </Keyframe>
        <Keyframe>
          <Time>76.92</Time>
          <Value>90</Value>
        </Keyframe>
        <Keyframe>
          <Time>77.02</Time>
          <Value>90</Value>
        </Keyframe>
        <Keyframe>
          <Time>77.22</Time>
          <Value>-90</Value>
        </Keyframe>
        <Keyframe>
          <Time>77.27</Time>
          <Value>0</Value>
        </Keyframe>
        <Keyframe>
          <Time>78.38</Time>
          <Value>0</Value>
        </Keyframe>
        <Keyframe>
          <Time>78.49</Time>
          <Value>-270</Value>
        </Keyframe>
        <Keyframe>
          <Time>79.12</Time>
          <Value>-270</Value>
        </Keyframe>
        <Keyframe>
          <Time>79.3</Time>
          <Value>-90</Value>
        </Keyframe>
        <Keyframe>
          <Time>79.34</Time>
          <Value>-90</Value>
        </Keyframe>
        <Keyframe>
          <Time>79.59</Time>
          <Value>90</Value>
        </Keyframe>
        <Keyframe>
          <Time>80.4156</Time>
          <Value>90</Value>
        </Keyframe>
        <Keyframe>
          <Time>80.5956</Time>
          <Value>-90</Value>
        </Keyframe>
        <Keyframe>
          <Time>80.6356</Time>
          <Value>-90</Value>
        </Keyframe>
        <Keyframe>
          <Time>80.7556</Time>
          <Value>-270</Value>
        </Keyframe>
        <Keyframe>
          <Time>80.8556</Time>
          <Value>-270</Value>
        </Keyframe>
        <Keyframe>
          <Time>81.0556</Time>
          <Value>0</Value>
        </Keyframe>
        <Keyframe>
          <Time>81.1</Time>
          <Value>-90</Value>
        </Keyframe>
        <Keyframe>
          <Time>81.22</Time>
          <Value>90</Value>
        </Keyframe>
        <Keyframe>
          <Time>81.32</Time>
          <Value>90</Value>
        </Keyframe>
        <Keyframe>
          <Time>81.52</Time>
          <Value>-90</Value>
        </Keyframe>
        <Keyframe>
          <Time>81.57</Time>
          <Value>-90</Value>
        </Keyframe>
        <Keyframe>
          <Time>81.67</Time>
          <Value>0</Value>
        </Keyframe>
        <Keyframe>
          <Time>82.78</Time>
          <Value>0</Value>
        </Keyframe>
        <Keyframe>
          <Time>82.89</Time>
          <Value>-270</Value>
        </Keyframe>
        <Keyframe>
          <Time>83.52</Time>
          <Value>-270</Value>
        </Keyframe>
        <Keyframe>
          <Time>83.7</Time>
          <Value>-90</Value>
        </Keyframe>
        <Keyframe>
          <Time>83.74</Time>
          <Value>-90</Value>
        </Keyframe>
        <Keyframe>
          <Time>83.99</Time>
          <Value>90</Value>
        </Keyframe>
        <Keyframe>
          <Time>84.8156</Time>
          <Value>90</Value>
        </Keyframe>
        <Keyframe>
          <Time>84.9956</Time>
          <Value>-90</Value>
        </Keyframe>
        <Keyframe>
          <Time>85.0356</Time>
          <Value>-90</Value>
        </Keyframe>
        <Keyframe>
          <Time>85.1556</Time>
          <Value>-270</Value>
        </Keyframe>
        <Keyframe>
          <Time>85.2556</Time>
          <Value>-270</Value>
        </Keyframe>
        <Keyframe>
          <Time>85.4556</Time>
          <Value>0</Value>
        </Keyframe>
        <Keyframe>
          <Time>85.5</Time>
          <Value>-90</Value>
        </Keyframe>
        <Keyframe>
          <Time>85.62</Time>
          <Value>90</Value>
        </Keyframe>
        <Keyframe>
          <Time>85.72</Time>
          <Value>90</Value>
        </Keyframe>
        <Keyframe>
          <Time>85.92</Time>
          <Value>-90</Value>
        </Keyframe>
        <Keyframe>
          <Time>85.97</Time>
          <Value>0</Value>
        </Keyframe>
      </Keyframes>
    </Uniform>
    <Uniform>
      <UniformName>p23Translation</UniformName>
      <Keyframes>
        <Keyframe>
          <Time>0</Time>
          <Value>-1.5</Value>
        </Keyframe>
        <Keyframe>
          <Time>60.75</Time>
          <Value>-1.5</Value>
        </Keyframe>
        <Keyframe>
          <Time>61.15343</Time>
          <Value>-5</Value>
        </Keyframe>
        <Keyframe>
          <Time>69.77</Time>
          <Value>-5</Value>
        </Keyframe>
        <Keyframe>
          <Time>86.20164</Time>
          <Value>-5</Value>
        </Keyframe>
        <Keyframe>
          <Time>86.30164</Time>
          <Value>-1.5</Value>
        </Keyframe>
        <Keyframe>
          <Time>100</Time>
          <Value>-1.5</Value>
        </Keyframe>
      </Keyframes>
    </Uniform>
    <Uniform>
      <UniformName>p16Translation</UniformName>
      <Keyframes>
        <Keyframe>
          <Time>0</Time>
          <Value>7</Value>
        </Keyframe>
        <Keyframe>
          <Time>60.75</Time>
          <Value>7</Value>
        </Keyframe>
        <Keyframe>
          <Time>61.15343</Time>
          <Value>10.5</Value>
        </Keyframe>
        <Keyframe>
          <Time>69.77</Time>
          <Value>10.5</Value>
        </Keyframe>
        <Keyframe>
          <Time>86.20164</Time>
          <Value>10.5</Value>
        </Keyframe>
        <Keyframe>
          <Time>86.30164</Time>
          <Value>7</Value>
        </Keyframe>
        <Keyframe>
          <Time>100</Time>
          <Value>7</Value>
        </Keyframe>
      </Keyframes>
    </Uniform>
    <Uniform>
      <UniformName>p1Rotation</UniformName>
      <Keyframes>
        <Keyframe>
          <Time>0</Time>
          <Value>-90</Value>
        </Keyframe>
        <Keyframe>
          <Time>62.24</Time>
          <Value>-90</Value>
        </Keyframe>
        <Keyframe>
          <Time>62.36</Time>
          <Value>90</Value>
        </Keyframe>
        <Keyframe>
          <Time>63.1156</Time>
          <Value>90</Value>
        </Keyframe>
        <Keyframe>
          <Time>63.3156</Time>
          <Value>-90</Value>
        </Keyframe>
        <Keyframe>
          <Time>63.4956</Time>
          <Value>90</Value>
        </Keyframe>
        <Keyframe>
          <Time>63.5356</Time>
          <Value>90</Value>
        </Keyframe>
        <Keyframe>
          <Time>63.6556</Time>
          <Value>-90</Value>
        </Keyframe>
        <Keyframe>
          <Time>63.7556</Time>
          <Value>-90</Value>
        </Keyframe>
        <Keyframe>
          <Time>63.9556</Time>
          <Value>-270</Value>
        </Keyframe>
        <Keyframe>
          <Time>64</Time>
          <Value>-270</Value>
        </Keyframe>
        <Keyframe>
          <Time>64.12</Time>
          <Value>0</Value>
        </Keyframe>
        <Keyframe>
          <Time>64.22</Time>
          <Value>-90</Value>
        </Keyframe>
        <Keyframe>
          <Time>64.42</Time>
          <Value>90</Value>
        </Keyframe>
        <Keyframe>
          <Time>64.47</Time>
          <Value>90</Value>
        </Keyframe>
        <Keyframe>
          <Time>64.57</Time>
          <Value>-90</Value>
        </Keyframe>
        <Keyframe>
          <Time>72.97</Time>
          <Value>-90</Value>
        </Keyframe>
        <Keyframe>
          <Time>74.08</Time>
          <Value>90</Value>
        </Keyframe>
        <Keyframe>
          <Time>74.19</Time>
          <Value>-270</Value>
        </Keyframe>
        <Keyframe>
          <Time>74.82</Time>
          <Value>-270</Value>
        </Keyframe>
        <Keyframe>
          <Time>75</Time>
          <Value>-90</Value>
        </Keyframe>
        <Keyframe>
          <Time>75.04</Time>
          <Value>-90</Value>
        </Keyframe>
        <Keyframe>
          <Time>75.29</Time>
          <Value>90</Value>
        </Keyframe>
        <Keyframe>
          <Time>76.1156</Time>
          <Value>90</Value>
        </Keyframe>
        <Keyframe>
          <Time>76.2956</Time>
          <Value>-90</Value>
        </Keyframe>
        <Keyframe>
          <Time>76.3356</Time>
          <Value>-90</Value>
        </Keyframe>
        <Keyframe>
          <Time>76.4556</Time>
          <Value>-270</Value>
        </Keyframe>
        <Keyframe>
          <Time>76.5556</Time>
          <Value>-270</Value>
        </Keyframe>
        <Keyframe>
          <Time>76.7556</Time>
          <Value>0</Value>
        </Keyframe>
        <Keyframe>
          <Time>76.8</Time>
          <Value>-90</Value>
        </Keyframe>
        <Keyframe>
          <Time>76.92</Time>
          <Value>90</Value>
        </Keyframe>
        <Keyframe>
          <Time>77.02</Time>
          <Value>90</Value>
        </Keyframe>
        <Keyframe>
          <Time>77.22</Time>
          <Value>-90</Value>
        </Keyframe>
        <Keyframe>
          <Time>77.27</Time>
          <Value>-90</Value>
        </Keyframe>
        <Keyframe>
          <Time>78.38</Time>
          <Value>-90</Value>
        </Keyframe>
        <Keyframe>
          <Time>78.49</Time>
          <Value>-270</Value>
        </Keyframe>
        <Keyframe>
          <Time>79.12</Time>
          <Value>-270</Value>
        </Keyframe>
        <Keyframe>
          <Time>79.3</Time>
          <Value>-90</Value>
        </Keyframe>
        <Keyframe>
          <Time>79.34</Time>
          <Value>-90</Value>
        </Keyframe>
        <Keyframe>
          <Time>79.59</Time>
          <Value>90</Value>
        </Keyframe>
        <Keyframe>
          <Time>80.4156</Time>
          <Value>90</Value>
        </Keyframe>
        <Keyframe>
          <Time>80.5956</Time>
          <Value>-90</Value>
        </Keyframe>
        <Keyframe>
          <Time>80.6356</Time>
          <Value>-90</Value>
        </Keyframe>
        <Keyframe>
          <Time>80.7556</Time>
          <Value>-270</Value>
        </Keyframe>
        <Keyframe>
          <Time>80.8556</Time>
          <Value>-270</Value>
        </Keyframe>
        <Keyframe>
          <Time>81.0556</Time>
          <Value>0</Value>
        </Keyframe>
        <Keyframe>
          <Time>81.1</Time>
          <Value>-90</Value>
        </Keyframe>
        <Keyframe>
          <Time>81.22</Time>
          <Value>90</Value>
        </Keyframe>
        <Keyframe>
          <Time>81.32</Time>
          <Value>90</Value>
        </Keyframe>
        <Keyframe>
          <Time>81.52</Time>
          <Value>-90</Value>
        </Keyframe>
        <Keyframe>
          <Time>81.57</Time>
          <Value>-90</Value>
        </Keyframe>
        <Keyframe>
          <Time>81.67</Time>
          <Value>-90</Value>
        </Keyframe>
        <Keyframe>
          <Time>82.78</Time>
          <Value>-90</Value>
        </Keyframe>
        <Keyframe>
          <Time>82.89</Time>
          <Value>-270</Value>
        </Keyframe>
        <Keyframe>
          <Time>83.52</Time>
          <Value>-270</Value>
        </Keyframe>
        <Keyframe>
          <Time>83.7</Time>
          <Value>-90</Value>
        </Keyframe>
        <Keyframe>
          <Time>83.74</Time>
          <Value>-90</Value>
        </Keyframe>
        <Keyframe>
          <Time>83.99</Time>
          <Value>90</Value>
        </Keyframe>
        <Keyframe>
          <Time>84.8156</Time>
          <Value>90</Value>
        </Keyframe>
        <Keyframe>
          <Time>84.9956</Time>
          <Value>-90</Value>
        </Keyframe>
        <Keyframe>
          <Time>85.0356</Time>
          <Value>-90</Value>
        </Keyframe>
        <Keyframe>
          <Time>85.1556</Time>
          <Value>-270</Value>
        </Keyframe>
        <Keyframe>
          <Time>85.2556</Time>
          <Value>-270</Value>
        </Keyframe>
        <Keyframe>
          <Time>85.4556</Time>
          <Value>0</Value>
        </Keyframe>
        <Keyframe>
          <Time>85.5</Time>
          <Value>-90</Value>
        </Keyframe>
        <Keyframe>
          <Time>85.62</Time>
          <Value>90</Value>
        </Keyframe>
        <Keyframe>
          <Time>85.72</Time>
          <Value>90</Value>
        </Keyframe>
        <Keyframe>
          <Time>85.92</Time>
          <Value>-90</Value>
        </Keyframe>
        <Keyframe>
          <Time>85.97</Time>
          <Value>-90</Value>
        </Keyframe>
      </Keyframes>
    </Uniform>
    <Uniform>
      <UniformName>diamondCamRotateZ</UniformName>
      <Keyframes>
        <Keyframe>
          <Time>95.94</Time>
          <Value>0</Value>
        </Keyframe>
        <Keyframe>
          <Time>96.58647</Time>
          <Value>0</Value>
        </Keyframe>
        <Keyframe>
          <Time>100.410423</Time>
          <Value>0</Value>
        </Keyframe>
        <Keyframe>
          <Time>102.780045</Time>
          <Value>90</Value>
        </Keyframe>
        <Keyframe>
          <Time>103.149544</Time>
          <Value>90</Value>
        </Keyframe>
        <Keyframe>
          <Time>104.869026</Time>
          <Value>90</Value>
        </Keyframe>
        <Keyframe>
          <Time>107.094063</Time>
          <Value>90</Value>
        </Keyframe>
        <Keyframe>
          <Time>109.132423</Time>
          <Value>90</Value>
        </Keyframe>
        <Keyframe>
          <Time>109.3151</Time>
          <Value>90</Value>
        </Keyframe>
        <Keyframe>
          <Time>111.448074</Time>
          <Value>90</Value>
        </Keyframe>
        <Keyframe>
          <Time>113.479515</Time>
          <Value>90</Value>
        </Keyframe>
        <Keyframe>
          <Time>117.822693</Time>
          <Value>90</Value>
        </Keyframe>
        <Keyframe>
          <Time>120.0385</Time>
          <Value>90</Value>
        </Keyframe>
        <Keyframe>
          <Time>122.354126</Time>
          <Value>90</Value>
        </Keyframe>
        <Keyframe>
          <Time>126.573547</Time>
          <Value>90</Value>
        </Keyframe>
        <Keyframe>
          <Time>130.984634</Time>
          <Value>90</Value>
        </Keyframe>
      </Keyframes>
    </Uniform>
    <Uniform>
      <UniformName>diamondCamRodiamondCamRotateXtateX</UniformName>
      <Keyframes>
        <Keyframe>
          <Time>95.94</Time>
          <Value>0</Value>
        </Keyframe>
        <Keyframe>
          <Time>100.568748</Time>
          <Value>90</Value>
        </Keyframe>
        <Keyframe>
          <Time>105.00589</Time>
          <Value>90</Value>
        </Keyframe>
        <Keyframe>
          <Time>109.256233</Time>
          <Value>90</Value>
        </Keyframe>
      </Keyframes>
    </Uniform>
    <Uniform>
      <UniformName>diamondCamRotateY</UniformName>
      <Keyframes>
        <Keyframe>
          <Time>95.94</Time>
          <Value>0</Value>
        </Keyframe>
        <Keyframe>
          <Time>100.410423</Time>
          <Value>0</Value>
        </Keyframe>
        <Keyframe>
          <Time>102.592468</Time>
          <Value>0</Value>
        </Keyframe>
        <Keyframe>
          <Time>104.869026</Time>
          <Value>0</Value>
        </Keyframe>
        <Keyframe>
          <Time>107.094063</Time>
          <Value>0</Value>
        </Keyframe>
        <Keyframe>
          <Time>109.3151</Time>
          <Value>180</Value>
        </Keyframe>
        <Keyframe>
          <Time>109.402359</Time>
          <Value>180</Value>
        </Keyframe>
        <Keyframe>
          <Time>111.448074</Time>
          <Value>180</Value>
        </Keyframe>
        <Keyframe>
          <Time>113.479515</Time>
          <Value>180</Value>
        </Keyframe>
        <Keyframe>
          <Time>113.54</Time>
          <Value>180</Value>
        </Keyframe>
        <Keyframe>
          <Time>118.1</Time>
          <Value>270</Value>
        </Keyframe>
        <Keyframe>
          <Time>120.0385</Time>
          <Value>270</Value>
        </Keyframe>
        <Keyframe>
          <Time>120.37</Time>
          <Value>270</Value>
        </Keyframe>
        <Keyframe>
          <Time>122.354126</Time>
          <Value>180</Value>
        </Keyframe>
        <Keyframe>
          <Time>126.49</Time>
          <Value>180</Value>
        </Keyframe>
        <Keyframe>
          <Time>131.088165</Time>
          <Value>0</Value>
        </Keyframe>
      </Keyframes>
    </Uniform>
    <Uniform>
      <UniformName>diamondCamRotateX</UniformName>
      <Keyframes>
        <Keyframe>
          <Time>95.94</Time>
          <Value>0</Value>
        </Keyframe>
        <Keyframe>
          <Time>100.410423</Time>
          <Value>0</Value>
        </Keyframe>
        <Keyframe>
          <Time>102.780045</Time>
          <Value>90</Value>
        </Keyframe>
        <Keyframe>
          <Time>104.869026</Time>
          <Value>90</Value>
        </Keyframe>
        <Keyframe>
          <Time>107.094063</Time>
          <Value>90</Value>
        </Keyframe>
        <Keyframe>
          <Time>109.132423</Time>
          <Value>90</Value>
        </Keyframe>
        <Keyframe>
          <Time>109.3151</Time>
          <Value>90</Value>
        </Keyframe>
        <Keyframe>
          <Time>111.448074</Time>
          <Value>90</Value>
        </Keyframe>
        <Keyframe>
          <Time>113.54</Time>
          <Value>0</Value>
        </Keyframe>
        <Keyframe>
          <Time>117.822693</Time>
          <Value>0</Value>
        </Keyframe>
        <Keyframe>
          <Time>117.938072</Time>
          <Value>0</Value>
        </Keyframe>
        <Keyframe>
          <Time>120.0385</Time>
          <Value>0</Value>
        </Keyframe>
        <Keyframe>
          <Time>120.207115</Time>
          <Value>0</Value>
        </Keyframe>
        <Keyframe>
          <Time>122.354126</Time>
          <Value>0</Value>
        </Keyframe>
        <Keyframe>
          <Time>126.573547</Time>
          <Value>0</Value>
        </Keyframe>
        <Keyframe>
          <Time>126.720154</Time>
          <Value>0</Value>
        </Keyframe>
        <Keyframe>
          <Time>130.984634</Time>
          <Value>0</Value>
        </Keyframe>
        <Keyframe>
          <Time>131.088165</Time>
          <Value>0</Value>
        </Keyframe>
      </Keyframes>
    </Uniform>
    <Uniform>
      <UniformName>diamondCamPosX</UniformName>
      <Keyframes>
        <Keyframe>
          <Time>96.58647</Time>
          <Value>0</Value>
        </Keyframe>
        <Keyframe>
          <Time>100.410423</Time>
          <Value>0</Value>
        </Keyframe>
        <Keyframe>
          <Time>102.592468</Time>
          <Value>0</Value>
        </Keyframe>
        <Keyframe>
          <Time>109.132423</Time>
          <Value>0</Value>
        </Keyframe>
        <Keyframe>
          <Time>113.479515</Time>
          <Value>0</Value>
        </Keyframe>
        <Keyframe>
          <Time>117.822693</Time>
          <Value>25</Value>
        </Keyframe>
        <Keyframe>
          <Time>120.0385</Time>
          <Value>25</Value>
        </Keyframe>
        <Keyframe>
          <Time>126.573547</Time>
          <Value>50</Value>
        </Keyframe>
        <Keyframe>
          <Time>130.984634</Time>
          <Value>0</Value>
        </Keyframe>
      </Keyframes>
    </Uniform>
    <Uniform>
      <UniformName>diamondCamPosY</UniformName>
      <Keyframes>
        <Keyframe>
          <Time>96.58647</Time>
          <Value>0</Value>
        </Keyframe>
        <Keyframe>
          <Time>100.410423</Time>
          <Value>0</Value>
        </Keyframe>
        <Keyframe>
          <Time>102.592468</Time>
          <Value>0</Value>
        </Keyframe>
        <Keyframe>
          <Time>109.132423</Time>
          <Value>0</Value>
        </Keyframe>
        <Keyframe>
          <Time>113.479515</Time>
          <Value>50</Value>
        </Keyframe>
        <Keyframe>
          <Time>117.822693</Time>
          <Value>50</Value>
        </Keyframe>
        <Keyframe>
          <Time>120.0385</Time>
          <Value>50</Value>
        </Keyframe>
        <Keyframe>
          <Time>126.573547</Time>
          <Value>50</Value>
        </Keyframe>
        <Keyframe>
          <Time>130.984634</Time>
          <Value>50</Value>
        </Keyframe>
      </Keyframes>
    </Uniform>
    <Uniform>
      <UniformName>diamondCamPosZ</UniformName>
      <Keyframes>
        <Keyframe>
          <Time>96.58647</Time>
          <Value>0</Value>
        </Keyframe>
        <Keyframe>
          <Time>100.410423</Time>
          <Value>0</Value>
        </Keyframe>
        <Keyframe>
          <Time>102.83</Time>
          <Value>50</Value>
        </Keyframe>
        <Keyframe>
          <Time>109.132423</Time>
          <Value>50</Value>
        </Keyframe>
        <Keyframe>
          <Time>113.479515</Time>
          <Value>50</Value>
        </Keyframe>
        <Keyframe>
          <Time>117.822693</Time>
          <Value>50</Value>
        </Keyframe>
        <Keyframe>
          <Time>126.573547</Time>
          <Value>50</Value>
        </Keyframe>
        <Keyframe>
          <Time>130.984634</Time>
          <Value>50</Value>
        </Keyframe>
      </Keyframes>
    </Uniform>
    <Uniform>
      <UniformName>iCamPosX</UniformName>
      <Keyframes>
        <Keyframe>
          <Time>0</Time>
          <Value>0</Value>
        </Keyframe>
      </Keyframes>
    </Uniform>
    <Uniform>
      <UniformName>floating1</UniformName>
      <Keyframes>
        <Keyframe>
          <Time>180.1535</Time>
          <Value>50</Value>
        </Keyframe>
        <Keyframe>
          <Time>186.7341</Time>
          <Value>-25.0495911</Value>
        </Keyframe>
        <Keyframe>
          <Time>193.306</Time>
          <Value>-100</Value>
        </Keyframe>
      </Keyframes>
    </Uniform>
    <Uniform>
      <UniformName>floating2</UniformName>
      <Keyframes>
        <Keyframe>
          <Time>186.7341</Time>
          <Value>35</Value>
        </Keyframe>
        <Keyframe>
          <Time>193.306</Time>
          <Value>-80</Value>
        </Keyframe>
      </Keyframes>
    </Uniform>
    <Uniform>
      <UniformName>diceCamY</UniformName>
      <Keyframes>
        <Keyframe>
          <Time>0</Time>
          <Value>15.26052</Value>
        </Keyframe>
        <Keyframe>
          <Time>26.19</Time>
          <Value>23.8916</Value>
        </Keyframe>
        <Keyframe>
          <Time>34.94</Time>
          <Value>44.4704323</Value>
        </Keyframe>
        <Keyframe>
          <Time>34.95</Time>
          <Value>23</Value>
        </Keyframe>
        <Keyframe>
          <Time>87.9011154</Time>
          <Value>39.66781</Value>
        </Keyframe>
        <Keyframe>
          <Time>88.86622</Time>
          <Value>0</Value>
        </Keyframe>
        <Keyframe>
          <Time>103.253036</Time>
          <Value>11.8397741</Value>
        </Keyframe>
        <Keyframe>
          <Time>130.033981</Time>
          <Value>0</Value>
        </Keyframe>
        <Keyframe>
          <Time>140.693787</Time>
          <Value>8.423791</Value>
        </Keyframe>
        <Keyframe>
          <Time>161.4651</Time>
          <Value>9.032967</Value>
        </Keyframe>
        <Keyframe>
          <Time>165.849213</Time>
          <Value>40</Value>
        </Keyframe>
        <Keyframe>
          <Time>174.776825</Time>
          <Value>40</Value>
        </Keyframe>
        <Keyframe>
          <Time>177.581879</Time>
          <Value>40</Value>
        </Keyframe>
      </Keyframes>
    </Uniform>
  </Uniforms>
  <Tracks>
    <Track>
      <Name>sum</Name>
      <ShaderKeyframes>
        <ShaderKeyframe>
          <Time>0</Time>
          <ShaderPath>.\vol_lines.glsl</ShaderPath>
        </ShaderKeyframe>
        <ShaderKeyframe>
          <Time>17.42</Time>
          <ShaderPath>.\cube_transition.glsl</ShaderPath>
        </ShaderKeyframe>
        <ShaderKeyframe>
          <Time>26.19</Time>
          <ShaderPath>.\DiceUniverse.glsl</ShaderPath>
        </ShaderKeyframe>
        <ShaderKeyframe>
          <Time>34.95</Time>
          <ShaderPath>.\cube_transition.glsl</ShaderPath>
        </ShaderKeyframe>
        <ShaderKeyframe>
          <Time>43.66</Time>
          <ShaderPath>.\CubeSpirale.glsl</ShaderPath>
        </ShaderKeyframe>
        <ShaderKeyframe>
          <Time>52.35</Time>
          <ShaderPath>.\cube_transition.glsl</ShaderPath>
        </ShaderKeyframe>
        <ShaderKeyframe>
          <Time>61.25</Time>
          <ShaderPath>.\Pyramids.glsl</ShaderPath>
        </ShaderKeyframe>
        <ShaderKeyframe>
          <Time>69.85</Time>
          <ShaderPath>.\cube_transition.glsl</ShaderPath>
        </ShaderKeyframe>
        <ShaderKeyframe>
          <Time>78.58</Time>
          <ShaderPath>.\Pyramids.glsl</ShaderPath>
        </ShaderKeyframe>
        <ShaderKeyframe>
          <Time>87.31</Time>
          <ShaderPath>.\cube_transition.glsl</ShaderPath>
        </ShaderKeyframe>
        <ShaderKeyframe>
          <Time>96.13</Time>
          <ShaderPath>.\Shader_DemoEvent.glsl</ShaderPath>
        </ShaderKeyframe>
        <ShaderKeyframe>
          <Time>131</Time>
          <ShaderPath>.\cube_transition.glsl</ShaderPath>
        </ShaderKeyframe>
        <ShaderKeyframe>
          <Time>139.84</Time>
          <ShaderPath>.\Second_Shader_Backup.glsl</ShaderPath>
        </ShaderKeyframe>
        <ShaderKeyframe>
          <Time>148.62</Time>
          <ShaderPath>.\cube_transition.glsl</ShaderPath>
        </ShaderKeyframe>
        <ShaderKeyframe>
          <Time>161.71</Time>
          <ShaderPath>.\DiceUniverse.glsl</ShaderPath>
        </ShaderKeyframe>
        <ShaderKeyframe>
          <Time>165.9</Time>
          <ShaderPath>.\RollTheDice.glsl</ShaderPath>
        </ShaderKeyframe>
        <ShaderKeyframe>
          <Time>174.77</Time>
          <ShaderPath>.\cube_transition.glsl</ShaderPath>
        </ShaderKeyframe>
        <ShaderKeyframe>
          <Time>183.3</Time>
          <ShaderPath>.\Outro_Shader.glsl</ShaderPath>
        </ShaderKeyframe>
      </ShaderKeyframes>
    </Track>
  </Tracks>
  <Textures>
    <string>.\diceBG.png</string>
    <string>.\diceTrans1.png</string>
  </Textures>
  <SoundFileName>.\ThomasTrack.mp3</SoundFileName>
</DemoData2>