<?xml version="1.0" encoding="utf-8"?>
<DemoData2 xmlns:xsd="http://www.w3.org/2001/XMLSchema" xmlns:xsi="http://www.w3.org/2001/XMLSchema-instance">
  <Uniforms>
    <Uniform>
      <UniformName>uMoveY</UniformName>
      <Keyframes>
        <Keyframe>
          <Time>0</Time>
          <Value>1</Value>
        </Keyframe>
        <Keyframe>
          <Time>10.8058605</Time>
          <Value>1</Value>
        </Keyframe>
        <Keyframe>
          <Time>11.8131866</Time>
          <Value>2</Value>
        </Keyframe>
      </Keyframes>
    </Uniform>
    <Uniform>
      <UniformName>uRepeatY</UniformName>
      <Keyframes>
        <Keyframe>
          <Time>0</Time>
          <Value>1</Value>
        </Keyframe>
        <Keyframe>
          <Time>10.8058605</Time>
          <Value>1</Value>
        </Keyframe>
        <Keyframe>
          <Time>11.8131866</Time>
          <Value>5</Value>
        </Keyframe>
      </Keyframes>
    </Uniform>
    <Uniform>
      <UniformName>uMoveX</UniformName>
      <Keyframes>
        <Keyframe>
          <Time>0</Time>
          <Value>1</Value>
        </Keyframe>
        <Keyframe>
          <Time>3.296704</Time>
          <Value>1</Value>
        </Keyframe>
        <Keyframe>
          <Time>4.212454</Time>
          <Value>2</Value>
        </Keyframe>
      </Keyframes>
    </Uniform>
    <Uniform>
      <UniformName>uRepeatZ</UniformName>
      <Keyframes>
        <Keyframe>
          <Time>0</Time>
          <Value>1</Value>
        </Keyframe>
        <Keyframe>
          <Time>5.6776557</Time>
          <Value>1</Value>
        </Keyframe>
        <Keyframe>
          <Time>6.227106</Time>
          <Value>5</Value>
        </Keyframe>
      </Keyframes>
    </Uniform>
    <Uniform>
      <UniformName>uRepeatX</UniformName>
      <Keyframes>
        <Keyframe>
          <Time>0</Time>
          <Value>1</Value>
        </Keyframe>
        <Keyframe>
          <Time>3.205128</Time>
          <Value>1</Value>
        </Keyframe>
        <Keyframe>
          <Time>3.296704</Time>
          <Value>5</Value>
        </Keyframe>
      </Keyframes>
    </Uniform>
    <Uniform>
      <UniformName>uMoveZ</UniformName>
      <Keyframes>
        <Keyframe>
          <Time>0</Time>
          <Value>1</Value>
        </Keyframe>
        <Keyframe>
          <Time>5.6776557</Time>
          <Value>1</Value>
        </Keyframe>
        <Keyframe>
          <Time>6.227106</Time>
          <Value>2</Value>
        </Keyframe>
      </Keyframes>
    </Uniform>
    <Uniform>
      <UniformName>uScale</UniformName>
      <Keyframes>
        <Keyframe>
          <Time>0</Time>
          <Value>0</Value>
        </Keyframe>
        <Keyframe>
          <Time>1.007326</Time>
          <Value>0</Value>
        </Keyframe>
        <Keyframe>
          <Time>1.55677652</Time>
          <Value>1</Value>
        </Keyframe>
      </Keyframes>
    </Uniform>
  </Uniforms>
  <Tracks>
    <Track>
      <Name>sum</Name>
      <ShaderKeyframes>
        <ShaderKeyframe>
          <Time>0</Time>
          <ShaderPath>.\vol_lines.glsl</ShaderPath>
        </ShaderKeyframe>
      </ShaderKeyframes>
    </Track>
  </Tracks>
  <Textures />
  <SoundFileName />
</DemoData2>